lift_make/__init__.py
lift_make/compiler.py
lift_make/dependency_graph.py
lift_make/file_modified_cache.py
lift_make/files.py
lift_make/helpers.py
lift_make/incremental.py
lift_make/lift.py
lift_make/lift_class.py
lift_make/print_color.py
lift_make/template_lift_build.py
lift_make/workers.py
lift_make-0.1.2.dist-info/METADATA
lift_make-0.1.2.dist-info/WHEEL
lift_make-0.1.2.dist-info/entry_points.txt
lift_make-0.1.2.dist-info/licenses/LICENSE
lift_make-0.1.2.dist-info/RECORD
