Metadata-Version: 2.4
Name: lift_make
Version: 0.1.2
Summary: Lift is a CMAKE/makefile replacement for C built with Python (Similar cli to zig build or Rust Cargo)
Author-email: omniscient <17525998+omnisci3nce@users.noreply.github.com>
License-File: LICENSE
Requires-Python: >=3.13
